libpythonpro/__init__.py
libpythonpro/github_api.py
urb_libpythonpro-0.1.dist-info/LICENSE
urb_libpythonpro-0.1.dist-info/METADATA
urb_libpythonpro-0.1.dist-info/WHEEL
urb_libpythonpro-0.1.dist-info/top_level.txt
urb_libpythonpro-0.1.dist-info/RECORD
