Metadata-Version: 2.1
Name: urb-libpythonpro
Version: 0.1
Summary: Módulo para exemplificar construção de projetos Python no curso PyTools
Home-page: https://github.com/javanurbieta/libpythonpro
Author: Javan Urbieta
Author-email: olajava11@gmail.com
License: GNU AFFERO GENERAL PUBLIC LICENSE
Classifier: Development Status :: 2 - Pre-Alpha
Classifier: Environment :: Console
Classifier: Intended Audience :: Developers
Classifier: License :: OSI Approved :: GNU Affero General Public License v3 or later (AGPLv3+)
Classifier: Operating System :: OS Independent
Classifier: Programming Language :: Python
Classifier: Programming Language :: Python :: 3.6
Classifier: Framework :: Pytest
License-File: LICENSE
Requires-Dist: requests
